pytest_azure/__init__.py
pytest_azure/utils.py
pytest_azure-0.0.3.dist-info/LICENSE
pytest_azure-0.0.3.dist-info/WHEEL
pytest_azure-0.0.3.dist-info/METADATA
pytest_azure-0.0.3.dist-info/RECORD
