Metadata-Version: 2.1
Name: pytest-azure
Version: 0.0.3
Summary: Pytest utilities and mocks for Azure
Author-email: Daniel Ciborowski <dciborow@microsoft.com>
Requires-Python: >=3.7
Classifier: Development Status :: 3 - Alpha
Classifier: Intended Audience :: Developers
Classifier: License :: OSI Approved :: MIT License
Classifier: Programming Language :: Python :: 3 :: Only
Classifier: Programming Language :: Python :: 3.7
Classifier: Programming Language :: Python :: 3.8
Classifier: Programming Language :: Python :: 3.9
Classifier: Programming Language :: Python :: 3.10
Requires-Dist: azure-common
Requires-Dist: azure-identity>=1.4.1
Requires-Dist: azure-keyvault>=4.1.0
Requires-Dist: azure-mgmt-authorization>=3.0.0
Requires-Dist: azure-mgmt-compute>=20.0.0
Requires-Dist: azure-mgmt-containerservice
Requires-Dist: azure-mgmt-resource>=12.1.0
Requires-Dist: kubernetes
Requires-Dist: msrestazure>=0.6.4
Requires-Dist: python-dotenv>=0.14.0
Requires-Dist: pytest
Requires-Dist: requests
Requires-Dist: bandit[toml]==1.7.4 ; extra == "test"
Requires-Dist: black==22.1.0 ; extra == "test"
Requires-Dist: check-manifest==0.48 ; extra == "test"
Requires-Dist: flake8-bugbear==22.1.11 ; extra == "test"
Requires-Dist: flake8-docstrings ; extra == "test"
Requires-Dist: flake8-formatter_junit_xml ; extra == "test"
Requires-Dist: flake8==4.0.1 ; extra == "test"
Requires-Dist: pre-commit==2.17.0 ; extra == "test"
Requires-Dist: pylint==2.12.2 ; extra == "test"
Requires-Dist: pylint_junit ; extra == "test"
Requires-Dist: pytest-cov==3.0.0 ; extra == "test"
Requires-Dist: pytest-mock<3.7.1 ; extra == "test"
Requires-Dist: pytest-runner ; extra == "test"
Requires-Dist: pytest==7.1.0 ; extra == "test"
Requires-Dist: pytest-github-actions-annotate-failures ; extra == "test"
Requires-Dist: shellcheck-py==0.8.0.4 ; extra == "test"
Project-URL: Documentation, https://github.com/microsoft/python-package-template/tree/main#readme
Project-URL: Source, https://github.com/microsoft/python-package-template
Project-URL: Tracker, https://github.com/microsoft/python-package-template/issues
Provides-Extra: test
